fuzzyevolve/__init__.py
fuzzyevolve/cli.py
fuzzyevolve/config.py
fuzzyevolve/reporting.py
fuzzyevolve/run_store.py
fuzzyevolve/adapters/__init__.py
fuzzyevolve/adapters/llm/__init__.py
fuzzyevolve/adapters/llm/critic.py
fuzzyevolve/adapters/llm/ensemble.py
fuzzyevolve/adapters/llm/operators.py
fuzzyevolve/adapters/llm/prompts.py
fuzzyevolve/adapters/llm/ranker.py
fuzzyevolve/console/__init__.py
fuzzyevolve/console/logging.py
fuzzyevolve/core/__init__.py
fuzzyevolve/core/anchors.py
fuzzyevolve/core/battle.py
fuzzyevolve/core/critique.py
fuzzyevolve/core/embeddings.py
fuzzyevolve/core/engine.py
fuzzyevolve/core/models.py
fuzzyevolve/core/mutation.py
fuzzyevolve/core/pool.py
fuzzyevolve/core/ports.py
fuzzyevolve/core/ratings.py
fuzzyevolve/core/selection.py
fuzzyevolve/tui/__init__.py
fuzzyevolve/tui/app.py
fuzzyevolve/tui/run_data.py
fuzzyevolve-0.2.2.dist-info/METADATA
fuzzyevolve-0.2.2.dist-info/WHEEL
fuzzyevolve-0.2.2.dist-info/entry_points.txt
fuzzyevolve-0.2.2.dist-info/licenses/LICENSE
fuzzyevolve-0.2.2.dist-info/RECORD
