Metadata-Version: 2.4
Name: fuzzyevolve
Version: 0.2.2
Summary: AlphaEvolve with fuzzy evaluation. Evolve anything, not just code.
Project-URL: Homepage, https://github.com/caesarnine/fuzzyevolve
Project-URL: Repository, https://github.com/caesarnine/fuzzyevolve
Project-URL: Issues, https://github.com/caesarnine/fuzzyevolve/issues
Author: caesarnine
License-Expression: Apache-2.0
License-File: LICENSE
Keywords: evolution,llm,map-elites,textual,trueskill
Classifier: Development Status :: 3 - Alpha
Classifier: Environment :: Console
Classifier: Intended Audience :: Developers
Classifier: License :: OSI Approved :: Apache Software License
Classifier: Operating System :: OS Independent
Classifier: Programming Language :: Python :: 3
Classifier: Programming Language :: Python :: 3.10
Classifier: Programming Language :: Python :: 3.11
Classifier: Programming Language :: Python :: 3.12
Classifier: Topic :: Software Development
Classifier: Topic :: Utilities
Requires-Python: >=3.10
Requires-Dist: google-genai>=0.3.0
Requires-Dist: numpy>=2.2.6
Requires-Dist: pydantic-ai>=0.0.49
Requires-Dist: pydantic>=2.0.0
Requires-Dist: rich>=13.9.4
Requires-Dist: sentence-transformers>=2.6.1
Requires-Dist: textual>=0.60.0
Requires-Dist: tomli>=2.0.1; python_version < '3.11'
Requires-Dist: trueskill>=0.4.5
Requires-Dist: typer>=0.12.3
Provides-Extra: dev
Requires-Dist: build>=1.2.1; extra == 'dev'
Requires-Dist: ipykernel>=6.29.5; extra == 'dev'
Requires-Dist: mypy>=1.0.0; extra == 'dev'
Requires-Dist: pre-commit>=3.7.1; extra == 'dev'
Requires-Dist: pytest>=7.0.0; extra == 'dev'
Requires-Dist: ruff>=0.1.0; extra == 'dev'
Requires-Dist: twine>=5.0.0; extra == 'dev'
Provides-Extra: vertex
Requires-Dist: google-cloud-aiplatform>=1.48.0; extra == 'vertex'
